kars/__init__.py
kars/karsft.py
kars/split_data.py
kars/xv.py
kars-0.0.0.9000.dist-info/LICENSE
kars-0.0.0.9000.dist-info/METADATA
kars-0.0.0.9000.dist-info/WHEEL
kars-0.0.0.9000.dist-info/top_level.txt
kars-0.0.0.9000.dist-info/zip-safe
kars-0.0.0.9000.dist-info/RECORD
