Metadata-Version: 2.1
Name: kars
Version: 0.0.0.9000
Summary: Kernel Approximation to Raman Spectra
Home-page: https://gjhunt.github.io/kars/
Author: Gregory J. Hunt
Author-email: ghunt@wm.edu
License: GPL3
Platform: UNKNOWN
Classifier: Programming Language :: Python :: 3
Classifier: License :: OSI Approved :: GNU General Public License v3 or later (GPLv3+)
Classifier: Operating System :: OS Independent
Classifier: Topic :: Scientific/Engineering
Requires-Dist: numpy
Requires-Dist: scipy
